tainers/__init__.py
tainers/tainer.py
tainers-0.3.1.dist-info/LICENSE
tainers-0.3.1.dist-info/METADATA
tainers-0.3.1.dist-info/WHEEL
tainers-0.3.1.dist-info/RECORD
