Metadata-Version: 2.1
Name: tainers
Version: 0.3.1
Summary: Simple replacement for testcontainers-python
License: MIT
Author: aperullo
Author-email: 18688190+aperullo@users.noreply.github.com
Requires-Python: >=3.8,<4.0
Classifier: License :: OSI Approved :: MIT License
Classifier: Programming Language :: Python :: 3
Classifier: Programming Language :: Python :: 3.8
Classifier: Programming Language :: Python :: 3.9
Classifier: Programming Language :: Python :: 3.10
Classifier: Programming Language :: Python :: 3.11
Classifier: Programming Language :: Python :: 3.12
Requires-Dist: docker (>=7.0.0)
